obiba_opal/__init__.py
obiba_opal/analysis.py
obiba_opal/console.py
obiba_opal/core.py
obiba_opal/data.py
obiba_opal/dictionary.py
obiba_opal/exports.py
obiba_opal/file.py
obiba_opal/imports.py
obiba_opal/io.py
obiba_opal/perm.py
obiba_opal/project.py
obiba_opal/security.py
obiba_opal/sql.py
obiba_opal/subjects.py
obiba_opal/system.py
obiba_opal/table.py
obiba_opal-5.3.0.dist-info/LICENSE.txt
obiba_opal-5.3.0.dist-info/METADATA
obiba_opal-5.3.0.dist-info/WHEEL
obiba_opal-5.3.0.dist-info/entry_points.txt
obiba_opal-5.3.0.dist-info/RECORD
