Metadata-Version: 2.3
Name: obiba-opal
Version: 5.3.0
Summary: OBiBa/Opal python client.
License: GPL-v3
Author: Yannick Marcon
Author-email: yannick.marcon@obiba.org
Maintainer: Yannick Marcon
Maintainer-email: yannick.marcon@obiba.org
Requires-Python: >=3.7,<4.0
Classifier: License :: Other/Proprietary License
Classifier: Programming Language :: Python :: 3
Classifier: Programming Language :: Python :: 3.7
Classifier: Programming Language :: Python :: 3.8
Classifier: Programming Language :: Python :: 3.9
Classifier: Programming Language :: Python :: 3.10
Classifier: Programming Language :: Python :: 3.11
Classifier: Programming Language :: Python :: 3.12
Classifier: Programming Language :: Python :: 3.13
Requires-Dist: requests (>=2.31.0,<3.0.0)
Requires-Dist: urllib3 (==1.26.17) ; python_version < "3.8"
Requires-Dist: urllib3 (>=2.0,<3.0) ; python_version >= "3.8" and python_version < "4.0"
Project-URL: Bug Tracker, https://github.com/obiba/opal-python-client/issues
Project-URL: Documentation, https://opaldoc.obiba.org/en/latest/python-user-guide/
Project-URL: Homepage, https://www.obiba.org
Project-URL: Repository, https://github.com/obiba/opal-python-client
